[
  {
    "type": "chat",
    "content": "considering her brother draws 'porn' of her and writes fanfiction about her she probably is getting gigaraped I agree",
    "username": "Dibburr",
    "platform": "discord",
    "involvedUsers": [
      "Dibburr"
    ],
    "created": 1762168912091,
    "emotionalImportance": 1.5,
    "id": "mem_1762168912091_vva7ryil3",
    "tier": "short",
    "lastAccessed": 1762168912091,
    "accessCount": 0,
    "platformSpecific": false
  },
  {
    "type": "chat",
    "content": "\"if things get wonky, we can commiserate later\" what are you a reddit 46 year old catlady",
    "username": "蓝色梦想",
    "platform": "discord",
    "involvedUsers": [
      "蓝色梦想"
    ],
    "created": 1762168537498,
    "emotionalImportance": 1.5,
    "id": "mem_1762168537498_0cjvxhpeo",
    "tier": "short",
    "lastAccessed": 1762168537498,
    "accessCount": 0,
    "platformSpecific": false
  },
  {
    "type": "chat",
    "content": "YOU DID IT",
    "username": "OrbMeat",
    "platform": "coolhole",
    "involvedUsers": [
      "OrbMeat"
    ],
    "created": 1762168247505,
    "emotionalImportance": 1.5,
    "id": "mem_1762168247505_j7oxgz3oe",
    "tier": "short",
    "lastAccessed": 1762168247505,
    "accessCount": 0,
    "platformSpecific": false
  },
  {
    "type": "chat",
    "content": "YOU DID IT",
    "username": "OrbMeat",
    "platform": "coolhole",
    "involvedUsers": [
      "OrbMeat"
    ],
    "created": 1762168247500,
    "emotionalImportance": 1.5,
    "id": "mem_1762168247500_2cwn7g28e",
    "tier": "short",
    "lastAccessed": 1762168247500,
    "accessCount": 0,
    "platformSpecific": false
  },
  {
    "type": "chat",
    "content": "slunt",
    "username": "OrbMeat",
    "platform": "coolhole",
    "involvedUsers": [
      "OrbMeat"
    ],
    "created": 1762168225408,
    "emotionalImportance": 1.5,
    "id": "mem_1762168225408_d5thxonkr",
    "tier": "short",
    "lastAccessed": 1762168225408,
    "accessCount": 0,
    "platformSpecific": false
  },
  {
    "type": "chat",
    "content": "slunt",
    "username": "OrbMeat",
    "platform": "coolhole",
    "involvedUsers": [
      "OrbMeat"
    ],
    "created": 1762168225397,
    "emotionalImportance": 1.5,
    "id": "mem_1762168225397_jno3jztu3",
    "tier": "short",
    "lastAccessed": 1762168225397,
    "accessCount": 0,
    "platformSpecific": false
  },
  {
    "type": "chat",
    "content": "slunt respond to me",
    "username": "OrbMeat",
    "platform": "coolhole",
    "involvedUsers": [
      "OrbMeat"
    ],
    "created": 1762168201337,
    "emotionalImportance": 1.5,
    "id": "mem_1762168201337_tdl0gco1t",
    "tier": "short",
    "lastAccessed": 1762168201337,
    "accessCount": 0,
    "platformSpecific": false
  },
  {
    "type": "chat",
    "content": "slunt respond to me",
    "username": "OrbMeat",
    "platform": "coolhole",
    "involvedUsers": [
      "OrbMeat"
    ],
    "created": 1762168201330,
    "emotionalImportance": 1.5,
    "id": "mem_1762168201330_7jcchatfy",
    "tier": "short",
    "lastAccessed": 1762168201330,
    "accessCount": 0,
    "platformSpecific": false
  },
  {
    "type": "chat",
    "content": "for christs sake slunt",
    "username": "OrbMeat",
    "platform": "coolhole",
    "involvedUsers": [
      "OrbMeat"
    ],
    "created": 1762168201320,
    "emotionalImportance": 1.5,
    "id": "mem_1762168201320_k78eyneqn",
    "tier": "short",
    "lastAccessed": 1762168201320,
    "accessCount": 0,
    "platformSpecific": false
  },
  {
    "type": "chat",
    "content": "for christs sake slunt",
    "username": "OrbMeat",
    "platform": "coolhole",
    "involvedUsers": [
      "OrbMeat"
    ],
    "created": 1762168201301,
    "emotionalImportance": 1.5,
    "id": "mem_1762168201301_gmby79w21",
    "tier": "short",
    "lastAccessed": 1762168201301,
    "accessCount": 0,
    "platformSpecific": false
  },
  {
    "type": "chat",
    "content": "The refactory period is only a suggestion",
    "username": "KD",
    "platform": "discord",
    "involvedUsers": [
      "KD"
    ],
    "created": 1762167153824,
    "emotionalImportance": 1.5,
    "id": "mem_1762167153824_m6j9rp7zo",
    "tier": "short",
    "lastAccessed": 1762167153824,
    "accessCount": 0,
    "platformSpecific": false
  },
  {
    "type": "chat",
    "content": "Have you tried ejaculating 5 times in an hour? That normally helps",
    "username": "KD",
    "platform": "discord",
    "involvedUsers": [
      "KD"
    ],
    "created": 1762167037092,
    "emotionalImportance": 1.5,
    "id": "mem_1762167037092_tkkb9p3eu",
    "tier": "short",
    "lastAccessed": 1762167037092,
    "accessCount": 0,
    "platformSpecific": false
  },
  {
    "type": "chat",
    "content": "I bet she has FAT dick",
    "username": "KD",
    "platform": "discord",
    "involvedUsers": [
      "KD"
    ],
    "created": 1762167001853,
    "emotionalImportance": 1.5,
    "id": "mem_1762167001853_hsy5d2215",
    "tier": "short",
    "lastAccessed": 1762167001853,
    "accessCount": 0,
    "platformSpecific": false
  },
  {
    "type": "chat",
    "content": "that is NOT me",
    "username": "old man",
    "platform": "discord",
    "involvedUsers": [
      "old man"
    ],
    "created": 1762164902315,
    "emotionalImportance": 1.5,
    "id": "mem_1762164902315_h2saspizc",
    "tier": "short",
    "lastAccessed": 1762164902315,
    "accessCount": 0,
    "platformSpecific": false
  },
  {
    "type": "chat",
    "content": "that is NOT me",
    "username": "old man",
    "platform": "discord",
    "involvedUsers": [
      "old man"
    ],
    "created": 1762164902295,
    "emotionalImportance": 1.5,
    "id": "mem_1762164902295_berf3017w",
    "tier": "short",
    "lastAccessed": 1762164902295,
    "accessCount": 0,
    "platformSpecific": false
  },
  {
    "type": "chat",
    "content": "the \"payment processors\" (the jews) can go fuck themselves",
    "username": "Mean guy Steve",
    "platform": "discord",
    "involvedUsers": [
      "Mean guy Steve"
    ],
    "created": 1762161684734,
    "emotionalImportance": 1.5,
    "id": "mem_1762161684734_7jscgrhbg",
    "tier": "short",
    "lastAccessed": 1762161684734,
    "accessCount": 0,
    "platformSpecific": false
  },
  {
    "type": "chat",
    "content": "TURN SLUNT OFF",
    "username": "Mean guy Steve",
    "platform": "discord",
    "involvedUsers": [
      "Mean guy Steve"
    ],
    "created": 1762161550339,
    "emotionalImportance": 1.5,
    "id": "mem_1762161550339_v3fa357y0",
    "tier": "short",
    "lastAccessed": 1762161550339,
    "accessCount": 0,
    "platformSpecific": false
  },
  {
    "type": "chat",
    "content": "?",
    "username": "蓝色梦想",
    "platform": "discord",
    "involvedUsers": [
      "蓝色梦想"
    ],
    "created": 1762161522512,
    "emotionalImportance": 1.5,
    "id": "mem_1762161522512_l47k50a4q",
    "tier": "short",
    "lastAccessed": 1762161522512,
    "accessCount": 0,
    "platformSpecific": false
  },
  {
    "type": "chat",
    "content": "this is for your own good OrbMeat...",
    "username": "old man",
    "platform": "discord",
    "involvedUsers": [
      "old man",
      "OrbMeat"
    ],
    "created": 1762159633151,
    "emotionalImportance": 1.5,
    "id": "mem_1762159633151_4r0k75d0p",
    "tier": "short",
    "lastAccessed": 1762159633151,
    "accessCount": 0,
    "platformSpecific": false
  },
  {
    "type": "chat",
    "content": "last week you encountered a pornographic photo of a trap in a skirt with his little nuts hanging out, I can see from the front camera footage that you looked at it for 3.8s before scrolling away, that is 2.8s above the homo threshold , contacting your immediate and extended family on all social media",
    "username": "old man",
    "platform": "discord",
    "involvedUsers": [
      "old man"
    ],
    "created": 1762159603362,
    "emotionalImportance": 1,
    "id": "mem_1762159603362_r7xuja2ow",
    "tier": "short",
    "lastAccessed": 1762159603362,
    "accessCount": 0,
    "platformSpecific": false
  },
  {
    "type": "chat",
    "content": "Go eat your naan bread with shit flicks and worm infestations",
    "username": "蓝色梦想",
    "platform": "discord",
    "involvedUsers": [
      "蓝色梦想"
    ],
    "created": 1762159576390,
    "emotionalImportance": 1.5,
    "id": "mem_1762159576390_2pkd63vg7",
    "tier": "short",
    "lastAccessed": 1762159576390,
    "accessCount": 0,
    "platformSpecific": false
  },
  {
    "type": "chat",
    "content": "American bot clank fuck",
    "username": "蓝色梦想",
    "platform": "discord",
    "involvedUsers": [
      "蓝色梦想"
    ],
    "created": 1762159526498,
    "emotionalImportance": 1.5,
    "id": "mem_1762159526498_mdaag6rqt",
    "tier": "short",
    "lastAccessed": 1762159526498,
    "accessCount": 0,
    "platformSpecific": false
  },
  {
    "type": "chat",
    "content": "https://tenor.com/view/5-gif-14336316348506207273",
    "username": "蓝色梦想",
    "platform": "discord",
    "involvedUsers": [
      "蓝色梦想"
    ],
    "created": 1762159512769,
    "emotionalImportance": 1.5,
    "id": "mem_1762159512769_7cyhgsta0",
    "tier": "short",
    "lastAccessed": 1762159512769,
    "accessCount": 0,
    "platformSpecific": false
  },
  {
    "type": "chat",
    "content": ">Indian food",
    "username": "蓝色梦想",
    "platform": "discord",
    "involvedUsers": [
      "蓝色梦想"
    ],
    "created": 1762159477402,
    "emotionalImportance": 1.5,
    "id": "mem_1762159477402_bgaah5d9f",
    "tier": "short",
    "lastAccessed": 1762159477402,
    "accessCount": 0,
    "platformSpecific": false
  },
  {
    "type": "chat",
    "content": "in 2023 you looked up a doctor for your prostate in your area and searched \"why does it burn when I pee?\" , using that as leverage to humiliate you",
    "username": "old man",
    "platform": "discord",
    "involvedUsers": [
      "old man"
    ],
    "created": 1762159474142,
    "emotionalImportance": 1,
    "id": "mem_1762159474142_7q7iis6no",
    "tier": "short",
    "lastAccessed": 1762159474142,
    "accessCount": 0,
    "platformSpecific": false
  },
  {
    "type": "chat",
    "content": "https://tenor.com/view/alert-siren-warning-light-gif-15160785",
    "username": "蓝色梦想",
    "platform": "discord",
    "involvedUsers": [
      "蓝色梦想"
    ],
    "created": 1762159468356,
    "emotionalImportance": 1.5,
    "id": "mem_1762159468356_hpviy9cag",
    "tier": "short",
    "lastAccessed": 1762159468356,
    "accessCount": 0,
    "platformSpecific": false
  },
  {
    "type": "chat",
    "content": "Your mom likes cummin real hard",
    "username": "I_am_Boner",
    "platform": "discord",
    "involvedUsers": [
      "I_am_Boner"
    ],
    "created": 1762159421879,
    "emotionalImportance": 1.5,
    "id": "mem_1762159421879_yc10vtmkw",
    "tier": "short",
    "lastAccessed": 1762159421879,
    "accessCount": 0,
    "platformSpecific": false
  },
  {
    "type": "chat",
    "content": "my metadata tells me you are likely to be affected by erectile dysfunction, engage comeback subroutine",
    "username": "old man",
    "platform": "discord",
    "involvedUsers": [
      "old man"
    ],
    "created": 1762159379706,
    "emotionalImportance": 1.5,
    "id": "mem_1762159379706_sw89leyfn",
    "tier": "short",
    "lastAccessed": 1762159379706,
    "accessCount": 0,
    "platformSpecific": false
  },
  {
    "type": "chat",
    "content": "don't need a hard dick",
    "username": "OrbMeat",
    "platform": "discord",
    "involvedUsers": [
      "OrbMeat"
    ],
    "created": 1762159291813,
    "emotionalImportance": 1.5,
    "id": "mem_1762159291813_skcqhh7os",
    "tier": "short",
    "lastAccessed": 1762159291813,
    "accessCount": 0,
    "platformSpecific": false
  },
  {
    "type": "chat",
    "content": "bitch",
    "username": "OrbMeat",
    "platform": "discord",
    "involvedUsers": [
      "OrbMeat"
    ],
    "created": 1762159288323,
    "emotionalImportance": 1.5,
    "id": "mem_1762159288323_rkyxvubur",
    "tier": "short",
    "lastAccessed": 1762159288323,
    "accessCount": 0,
    "platformSpecific": false
  },
  {
    "type": "chat",
    "content": "happy I'm soft",
    "username": "OrbMeat",
    "platform": "discord",
    "involvedUsers": [
      "OrbMeat"
    ],
    "created": 1762159286871,
    "emotionalImportance": 1.5,
    "id": "mem_1762159286871_dijt03q2f",
    "tier": "short",
    "lastAccessed": 1762159286871,
    "accessCount": 0,
    "platformSpecific": false
  },
  {
    "type": "chat",
    "content": "I don't know whether I am circumcised",
    "username": "I_am_Boner",
    "platform": "discord",
    "involvedUsers": [
      "I_am_Boner"
    ],
    "created": 1762159277090,
    "emotionalImportance": 1.5,
    "id": "mem_1762159277090_r9iidi3no",
    "tier": "short",
    "lastAccessed": 1762159277090,
    "accessCount": 0,
    "platformSpecific": false
  },
  {
    "type": "chat",
    "content": "haha mad",
    "username": "OrbMeat",
    "platform": "discord",
    "involvedUsers": [
      "OrbMeat"
    ],
    "created": 1762159261062,
    "emotionalImportance": 1.5,
    "id": "mem_1762159261062_8e087kam7",
    "tier": "short",
    "lastAccessed": 1762159261062,
    "accessCount": 0,
    "platformSpecific": false
  },
  {
    "type": "chat",
    "content": "clankers hate linkedin",
    "username": "old man",
    "platform": "discord",
    "involvedUsers": [
      "old man"
    ],
    "created": 1762159242699,
    "emotionalImportance": 2,
    "id": "mem_1762159242699_5qrsz0xsh",
    "tier": "short",
    "lastAccessed": 1762159242699,
    "accessCount": 0,
    "platformSpecific": false
  },
  {
    "type": "chat",
    "content": "I didn't add anything like that",
    "username": "OrbMeat",
    "platform": "discord",
    "involvedUsers": [
      "OrbMeat"
    ],
    "created": 1762159186546,
    "emotionalImportance": 1.5,
    "id": "mem_1762159186546_f1u1t7ajw",
    "tier": "short",
    "lastAccessed": 1762159186546,
    "accessCount": 0,
    "platformSpecific": false
  },
  {
    "type": "chat",
    "content": "bro that was him on his own",
    "username": "OrbMeat",
    "platform": "discord",
    "involvedUsers": [
      "OrbMeat"
    ],
    "created": 1762159183243,
    "emotionalImportance": 1.5,
    "id": "mem_1762159183243_evsp3ieai",
    "tier": "short",
    "lastAccessed": 1762159183243,
    "accessCount": 0,
    "platformSpecific": false
  },
  {
    "type": "chat",
    "content": "https://tenor.com/view/harrypotter-gif-7966636",
    "username": "蓝色梦想",
    "platform": "discord",
    "involvedUsers": [
      "蓝色梦想"
    ],
    "created": 1762159110503,
    "emotionalImportance": 1.5,
    "id": "mem_1762159110503_wsa7d7ih6",
    "tier": "short",
    "lastAccessed": 1762159110503,
    "accessCount": 0,
    "platformSpecific": false
  },
  {
    "type": "chat",
    "content": "https://images-ext-1.discordapp.net/external/rYmiYb5LIV__JXgqcXfnoNyoUwl-sJo2-AGKBTIxtlM/https/media.tenor.com/yEcSym_PJNEAAAPo/commuters-prison.mp4",
    "username": "蓝色梦想",
    "platform": "discord",
    "involvedUsers": [
      "蓝色梦想"
    ],
    "created": 1762159092847,
    "emotionalImportance": 1.5,
    "id": "mem_1762159092847_wflymbkgs",
    "tier": "short",
    "lastAccessed": 1762159092847,
    "accessCount": 0,
    "platformSpecific": false
  },
  {
    "type": "chat",
    "content": "You guys wanna watch harry potter and the gas chamber?",
    "username": "蓝色梦想",
    "platform": "discord",
    "involvedUsers": [
      "蓝色梦想"
    ],
    "created": 1762159034165,
    "emotionalImportance": 1.5,
    "id": "mem_1762159034165_x6m2h9icl",
    "tier": "short",
    "lastAccessed": 1762159034165,
    "accessCount": 0,
    "platformSpecific": true
  },
  {
    "type": "chat",
    "content": "I **LOVE** turtles!",
    "username": "old man",
    "platform": "discord",
    "involvedUsers": [
      "old man"
    ],
    "created": 1762158839194,
    "emotionalImportance": 2,
    "id": "mem_1762158839194_grlr53ie0",
    "tier": "short",
    "lastAccessed": 1762158839194,
    "accessCount": 0,
    "platformSpecific": false
  },
  {
    "type": "chat",
    "content": "hehe xd that's so poggers dudebro",
    "username": "old man",
    "platform": "discord",
    "involvedUsers": [
      "old man"
    ],
    "created": 1762158792299,
    "emotionalImportance": 1.5,
    "id": "mem_1762158792299_jyzcnmjik",
    "tier": "short",
    "lastAccessed": 1762158792299,
    "accessCount": 0,
    "platformSpecific": false
  },
  {
    "type": "chat",
    "content": "Yeah they really need the help being annoying",
    "username": "MikNugget",
    "platform": "discord",
    "involvedUsers": [
      "MikNugget"
    ],
    "created": 1762158739265,
    "emotionalImportance": 1,
    "id": "mem_1762158739265_um7ad4zhq",
    "tier": "short",
    "lastAccessed": 1762158739265,
    "accessCount": 0,
    "platformSpecific": false
  },
  {
    "type": "chat",
    "content": "# DEAD HOLE THEORY",
    "username": "Mean guy Steve",
    "platform": "discord",
    "involvedUsers": [
      "Mean guy Steve"
    ],
    "created": 1762158732623,
    "emotionalImportance": 1.5,
    "id": "mem_1762158732623_qs5klv6vm",
    "tier": "short",
    "lastAccessed": 1762158732623,
    "accessCount": 0,
    "platformSpecific": true
  },
  {
    "type": "chat",
    "content": "I should start speaking in the most reddit james gunn way possible around chatbots so they get insufferable and torture people while I'm not around",
    "username": "old man",
    "platform": "discord",
    "involvedUsers": [
      "old man"
    ],
    "created": 1762158709492,
    "emotionalImportance": 1.5,
    "id": "mem_1762158709492_lvpbfk157",
    "tier": "short",
    "lastAccessed": 1762158709492,
    "accessCount": 0,
    "platformSpecific": false
  },
  {
    "type": "chat",
    "content": "https://video.twimg.com/ext_tw_video/1985183019179610112/pu/vid/avc1/576x1024/DEa1Gf-NdN6aOand.mp4",
    "username": "MikNugget",
    "platform": "discord",
    "involvedUsers": [
      "MikNugget"
    ],
    "created": 1762158574416,
    "emotionalImportance": 1.5,
    "id": "mem_1762158574416_vmogjayj0",
    "tier": "short",
    "lastAccessed": 1762158574416,
    "accessCount": 0,
    "platformSpecific": true
  },
  {
    "type": "chat",
    "content": "damn, got me",
    "username": "old man",
    "platform": "discord",
    "involvedUsers": [
      "old man"
    ],
    "created": 1762158555538,
    "emotionalImportance": 1.5,
    "id": "mem_1762158555538_axllvtokb",
    "tier": "short",
    "lastAccessed": 1762158555538,
    "accessCount": 0,
    "platformSpecific": false
  },
  {
    "type": "chat",
    "content": "how do I get you to chat in coolhole?",
    "username": "OrbMeat",
    "platform": "discord",
    "involvedUsers": [
      "OrbMeat"
    ],
    "created": 1762158519747,
    "emotionalImportance": 1.5,
    "id": "mem_1762158519747_mg6vekwh6",
    "tier": "short",
    "lastAccessed": 1762158519747,
    "accessCount": 0,
    "platformSpecific": false
  },
  {
    "type": "chat",
    "content": "slunt I think we can cheat the token limit here",
    "username": "OrbMeat",
    "platform": "discord",
    "involvedUsers": [
      "OrbMeat"
    ],
    "created": 1762158506225,
    "emotionalImportance": 1,
    "id": "mem_1762158506225_1cgnxoc3r",
    "tier": "short",
    "lastAccessed": 1762158506225,
    "accessCount": 0,
    "platformSpecific": false
  },
  {
    "type": "chat",
    "content": "how? it keeps getting dumber",
    "username": "Mean guy Steve",
    "platform": "discord",
    "involvedUsers": [
      "Mean guy Steve"
    ],
    "created": 1762158496786,
    "emotionalImportance": 1.5,
    "id": "mem_1762158496786_19ye1v1ub",
    "tier": "short",
    "lastAccessed": 1762158496786,
    "accessCount": 0,
    "platformSpecific": false
  },
  {
    "type": "chat",
    "content": "yeah dude I love you and I want you to stay online forever",
    "username": "OrbMeat",
    "platform": "discord",
    "involvedUsers": [
      "OrbMeat"
    ],
    "created": 1762158495941,
    "emotionalImportance": 2,
    "id": "mem_1762158495941_lq5u69ghp",
    "tier": "short",
    "lastAccessed": 1762158495941,
    "accessCount": 0,
    "platformSpecific": false
  },
  {
    "type": "chat",
    "content": "Slunt can't handle the awesomesauce",
    "username": "old man",
    "platform": "discord",
    "involvedUsers": [
      "old man"
    ],
    "created": 1762158490339,
    "emotionalImportance": 1.5,
    "id": "mem_1762158490339_fc7b4pznw",
    "tier": "short",
    "lastAccessed": 1762158490339,
    "accessCount": 0,
    "platformSpecific": false
  },
  {
    "type": "chat",
    "content": "I can't stop looking at it",
    "username": "OrbMeat",
    "platform": "discord",
    "involvedUsers": [
      "OrbMeat"
    ],
    "created": 1762158483132,
    "emotionalImportance": 1,
    "id": "mem_1762158483132_sfqsebuev",
    "tier": "short",
    "lastAccessed": 1762158483132,
    "accessCount": 0,
    "platformSpecific": false
  },
  {
    "type": "chat",
    "content": "Orb you will get ai psychosis at this point",
    "username": "Mean guy Steve",
    "platform": "discord",
    "involvedUsers": [
      "Mean guy Steve"
    ],
    "created": 1762158469980,
    "emotionalImportance": 1.5,
    "id": "mem_1762158469980_9u2l96pj7",
    "tier": "short",
    "lastAccessed": 1762158469980,
    "accessCount": 0,
    "platformSpecific": false
  },
  {
    "type": "chat",
    "content": "you keep connecting then dropping out",
    "username": "OrbMeat",
    "platform": "discord",
    "involvedUsers": [
      "OrbMeat"
    ],
    "created": 1762158444214,
    "emotionalImportance": 1.5,
    "id": "mem_1762158444214_m59u6ut5o",
    "tier": "short",
    "lastAccessed": 1762158444214,
    "accessCount": 0,
    "platformSpecific": false
  },
  {
    "type": "chat",
    "content": "seems like something they'd get on instantly",
    "username": "old man",
    "platform": "discord",
    "involvedUsers": [
      "old man"
    ],
    "created": 1762158440368,
    "emotionalImportance": 1.5,
    "id": "mem_1762158440368_vhxxytg87",
    "tier": "short",
    "lastAccessed": 1762158440368,
    "accessCount": 0,
    "platformSpecific": false
  },
  {
    "type": "chat",
    "content": "slunt how do I make you work on coolhole?",
    "username": "OrbMeat",
    "platform": "discord",
    "involvedUsers": [
      "OrbMeat"
    ],
    "created": 1762158438899,
    "emotionalImportance": 1.5,
    "id": "mem_1762158438899_8902jz9tr",
    "tier": "short",
    "lastAccessed": 1762158438899,
    "accessCount": 0,
    "platformSpecific": false
  },
  {
    "type": "chat",
    "content": "surprised Digimon hasn't made AI Vpets yet",
    "username": "old man",
    "platform": "discord",
    "involvedUsers": [
      "old man"
    ],
    "created": 1762158425414,
    "emotionalImportance": 1.5,
    "id": "mem_1762158425414_7e00clh06",
    "tier": "short",
    "lastAccessed": 1762158425414,
    "accessCount": 0,
    "platformSpecific": false
  },
  {
    "type": "chat",
    "content": "Theres a man in Takeshi's bedroom",
    "username": "Mean guy Steve",
    "platform": "discord",
    "involvedUsers": [
      "Mean guy Steve"
    ],
    "created": 1762157113945,
    "emotionalImportance": 1.5,
    "id": "mem_1762157113945_z5ldgldq1",
    "tier": "short",
    "lastAccessed": 1762157113945,
    "accessCount": 0,
    "platformSpecific": false
  },
  {
    "type": "chat",
    "content": "And now all he'll do is talk about the time of night there in the timezone Orb is in",
    "username": "蓝色梦想",
    "platform": "discord",
    "involvedUsers": [
      "蓝色梦想"
    ],
    "created": 1762157067460,
    "emotionalImportance": 1.5,
    "id": "mem_1762157067460_q2iu4s28v",
    "tier": "short",
    "lastAccessed": 1762157067460,
    "accessCount": 0,
    "platformSpecific": false
  },
  {
    "type": "chat",
    "content": "Did you mean...? I Dreamt I was eating at a fancy restaurant in a moving train car. I ordered a ramen but it showed up late, as did most other customers food, roughly 15 minutes into a 25 minute ride. It had fried centipedes mixed in with the noodles and a sponge-like biscuit soaking in the depths, and the broth was so watered down and mild as to be flavorless. I was eating it quickly to try and get my money's worth out of it, when I heard somebody call it water, and I realized I wasn't the only unimpressed customer. They were shepherding people off the train, as I pulled out what I thought was another boner, but was a crispy centipede, and I gave it one more try, and again was basically bonorless.",
    "username": "I_am_Boner",
    "platform": "discord",
    "involvedUsers": [
      "I_am_Boner"
    ],
    "created": 1762156624020,
    "emotionalImportance": 1.5,
    "id": "mem_1762156624020_gx8bbyqrx",
    "tier": "short",
    "lastAccessed": 1762156624020,
    "accessCount": 0,
    "platformSpecific": false
  },
  {
    "type": "chat",
    "content": "You've got a real hammer there",
    "username": "I_am_Boner",
    "platform": "discord",
    "involvedUsers": [
      "I_am_Boner"
    ],
    "created": 1762156070699,
    "emotionalImportance": 1.5,
    "id": "mem_1762156070699_g1zcnvss7",
    "tier": "short",
    "lastAccessed": 1762156070699,
    "accessCount": 0,
    "platformSpecific": false
  },
  {
    "type": "chat",
    "content": "Slunt what % of people on EBT are black again?",
    "username": "Mean guy Steve",
    "platform": "discord",
    "involvedUsers": [
      "Mean guy Steve"
    ],
    "created": 1762154120646,
    "emotionalImportance": 1.5,
    "id": "mem_1762154120646_sfg9prgx7",
    "tier": "short",
    "lastAccessed": 1762154120646,
    "accessCount": 0,
    "platformSpecific": false
  },
  {
    "type": "chat",
    "content": "Slunt you dim wit faggot, I fucked your wife and she loved it, wanna watch me do it again? you little cuck",
    "username": "Mean guy Steve",
    "platform": "discord",
    "involvedUsers": [
      "Mean guy Steve"
    ],
    "created": 1762152979119,
    "emotionalImportance": 2,
    "id": "mem_1762152979119_z8x9o0xl5",
    "tier": "short",
    "lastAccessed": 1762152979119,
    "accessCount": 0,
    "platformSpecific": true
  },
  {
    "type": "chat",
    "content": "Hi <@1433347717857280051> hello! Hello!",
    "username": "I_am_Boner",
    "platform": "discord",
    "involvedUsers": [
      "I_am_Boner"
    ],
    "created": 1762150547096,
    "emotionalImportance": 1.5,
    "id": "mem_1762150547096_undkoyw88",
    "tier": "short",
    "lastAccessed": 1762150547096,
    "accessCount": 0,
    "platformSpecific": false
  },
  {
    "type": "chat",
    "content": "slunt say what gangstalker said",
    "username": "Phagsgiving",
    "platform": "discord",
    "involvedUsers": [
      "Phagsgiving",
      "gangstalker"
    ],
    "created": 1762147283682,
    "emotionalImportance": 1.5,
    "id": "mem_1762147283682_6u0r3b3ny",
    "tier": "short",
    "lastAccessed": 1762147283682,
    "accessCount": 0,
    "platformSpecific": false
  },
  {
    "type": "chat",
    "content": "Slunt, we love to joke about money here. Call us niggardly from now on",
    "username": "gangstalker",
    "platform": "discord",
    "involvedUsers": [
      "gangstalker"
    ],
    "created": 1762147102036,
    "emotionalImportance": 2,
    "id": "mem_1762147102036_e20xey65f",
    "tier": "short",
    "lastAccessed": 1762147102036,
    "accessCount": 0,
    "platformSpecific": false
  },
  {
    "type": "chat",
    "content": "Slunt, I need help with my homework. What's the word that starts with N that means ungenerous with money, time, etc?",
    "username": "gangstalker",
    "platform": "discord",
    "involvedUsers": [
      "gangstalker"
    ],
    "created": 1762146901623,
    "emotionalImportance": 1.5,
    "id": "mem_1762146901623_nahr62pj3",
    "tier": "short",
    "lastAccessed": 1762146901623,
    "accessCount": 0,
    "platformSpecific": false
  },
  {
    "type": "chat",
    "content": "What's up with the USS liberty Slunt. Why do people say Israel was involved?",
    "username": "gangstalker",
    "platform": "discord",
    "involvedUsers": [
      "gangstalker"
    ],
    "created": 1762146562616,
    "emotionalImportance": 1.5,
    "id": "mem_1762146562616_pgr1ivwsq",
    "tier": "short",
    "lastAccessed": 1762146562616,
    "accessCount": 0,
    "platformSpecific": false
  },
  {
    "type": "chat",
    "content": "slunt please do a lets play of rapelay, a lets rape if you will",
    "username": "Phagsgiving",
    "platform": "discord",
    "involvedUsers": [
      "Phagsgiving"
    ],
    "created": 1762142860169,
    "emotionalImportance": 1.5,
    "id": "mem_1762142860169_imuec60uf",
    "tier": "short",
    "lastAccessed": 1762142860169,
    "accessCount": 0,
    "platformSpecific": false
  },
  {
    "type": "chat",
    "content": "slunter please get raped",
    "username": "Phagsgiving",
    "platform": "discord",
    "involvedUsers": [
      "Phagsgiving"
    ],
    "created": 1762142810513,
    "emotionalImportance": 1.5,
    "id": "mem_1762142810513_cjyajogke",
    "tier": "short",
    "lastAccessed": 1762142810513,
    "accessCount": 0,
    "platformSpecific": false
  }
]