{
  "relationships": {
    "theirin_theirin": {
      "users": [
        "theirin",
        "theirin"
      ],
      "interactions": 1,
      "positiveInteractions": 0,
      "negativeInteractions": 0,
      "tension": 0,
      "closeness": 1,
      "firstInteraction": 1762301283331,
      "lastInteraction": 1762301283331,
      "rumors": []
    },
    "You_You": {
      "users": [
        "You",
        "You"
      ],
      "interactions": 872,
      "positiveInteractions": 0,
      "negativeInteractions": 0,
      "tension": 0,
      "closeness": 100,
      "firstInteraction": 1762301438022,
      "lastInteraction": 1762333102220,
      "rumors": []
    },
    "Sithlord8448_Sithlord8448": {
      "users": [
        "Sithlord8448",
        "Sithlord8448"
      ],
      "interactions": 6,
      "positiveInteractions": 0,
      "negativeInteractions": 0,
      "tension": 0,
      "closeness": 6,
      "firstInteraction": 1762301516447,
      "lastInteraction": 1762321030917,
      "rumors": []
    },
    "handini__handini_": {
      "users": [
        "handini_",
        "handini_"
      ],
      "interactions": 7,
      "positiveInteractions": 0,
      "negativeInteractions": 0,
      "tension": 0,
      "closeness": 7,
      "firstInteraction": 1762301998867,
      "lastInteraction": 1762322356848,
      "rumors": []
    },
    "Capegourd_Capegourd": {
      "users": [
        "Capegourd",
        "Capegourd"
      ],
      "interactions": 15,
      "positiveInteractions": 0,
      "negativeInteractions": 0,
      "tension": 0,
      "closeness": 15,
      "firstInteraction": 1762303323122,
      "lastInteraction": 1762333058045,
      "rumors": []
    },
    "thankerware 🦃_thankerware 🦃": {
      "users": [
        "thankerware 🦃",
        "thankerware 🦃"
      ],
      "interactions": 2,
      "positiveInteractions": 0,
      "negativeInteractions": 0,
      "tension": 0,
      "closeness": 2,
      "firstInteraction": 1762304015956,
      "lastInteraction": 1762311228357,
      "rumors": []
    },
    "füg_füg": {
      "users": [
        "füg",
        "füg"
      ],
      "interactions": 1,
      "positiveInteractions": 0,
      "negativeInteractions": 0,
      "tension": 0,
      "closeness": 1,
      "firstInteraction": 1762304249767,
      "lastInteraction": 1762304249767,
      "rumors": []
    },
    "Soy Ant_Soy Ant": {
      "users": [
        "Soy Ant",
        "Soy Ant"
      ],
      "interactions": 2,
      "positiveInteractions": 0,
      "negativeInteractions": 0,
      "tension": 0,
      "closeness": 2,
      "firstInteraction": 1762304324810,
      "lastInteraction": 1762304329481,
      "rumors": []
    },
    "aSoapyoid_aSoapyoid": {
      "users": [
        "aSoapyoid",
        "aSoapyoid"
      ],
      "interactions": 1,
      "positiveInteractions": 0,
      "negativeInteractions": 0,
      "tension": 0,
      "closeness": 1,
      "firstInteraction": 1762308143002,
      "lastInteraction": 1762308143002,
      "rumors": []
    },
    "thank_________thank________": {
      "users": [
        "thank________",
        "thank________"
      ],
      "interactions": 3,
      "positiveInteractions": 0,
      "negativeInteractions": 0,
      "tension": 0,
      "closeness": 3,
      "firstInteraction": 1762308226266,
      "lastInteraction": 1762309072340,
      "rumors": []
    },
    "KR-B_KR-B": {
      "users": [
        "KR-B",
        "KR-B"
      ],
      "interactions": 1,
      "positiveInteractions": 0,
      "negativeInteractions": 0,
      "tension": 0,
      "closeness": 1,
      "firstInteraction": 1762308662873,
      "lastInteraction": 1762308662873,
      "rumors": []
    },
    "Davedalus_Davedalus": {
      "users": [
        "Davedalus",
        "Davedalus"
      ],
      "interactions": 11,
      "positiveInteractions": 0,
      "negativeInteractions": 0,
      "tension": 0,
      "closeness": 11,
      "firstInteraction": 1762308892843,
      "lastInteraction": 1762325194374,
      "rumors": []
    },
    "ZoomerTbagger2_ZoomerTbagger2": {
      "users": [
        "ZoomerTbagger2",
        "ZoomerTbagger2"
      ],
      "interactions": 1,
      "positiveInteractions": 0,
      "negativeInteractions": 0,
      "tension": 0,
      "closeness": 1,
      "firstInteraction": 1762309088059,
      "lastInteraction": 1762309088059,
      "rumors": []
    },
    "Shazbot_Shazbot": {
      "users": [
        "Shazbot",
        "Shazbot"
      ],
      "interactions": 2,
      "positiveInteractions": 0,
      "negativeInteractions": 0,
      "tension": 0,
      "closeness": 2,
      "firstInteraction": 1762309142523,
      "lastInteraction": 1762309152338,
      "rumors": []
    },
    "BbNaB_BbNaB": {
      "users": [
        "BbNaB",
        "BbNaB"
      ],
      "interactions": 1,
      "positiveInteractions": 0,
      "negativeInteractions": 0,
      "tension": 0,
      "closeness": 1,
      "firstInteraction": 1762309208289,
      "lastInteraction": 1762309208289,
      "rumors": []
    },
    "aSoapytyfys_aSoapytyfys": {
      "users": [
        "aSoapytyfys",
        "aSoapytyfys"
      ],
      "interactions": 3,
      "positiveInteractions": 0,
      "negativeInteractions": 0,
      "tension": 0,
      "closeness": 3,
      "firstInteraction": 1762309549821,
      "lastInteraction": 1762311986428,
      "rumors": []
    },
    "Secretsquirrel83_Secretsquirrel83": {
      "users": [
        "Secretsquirrel83",
        "Secretsquirrel83"
      ],
      "interactions": 2,
      "positiveInteractions": 0,
      "negativeInteractions": 0,
      "tension": 0,
      "closeness": 2,
      "firstInteraction": 1762310275876,
      "lastInteraction": 1762310280815,
      "rumors": []
    },
    "CHURCH1941_CHURCH1941": {
      "users": [
        "CHURCH1941",
        "CHURCH1941"
      ],
      "interactions": 2,
      "positiveInteractions": 0,
      "negativeInteractions": 0,
      "tension": 0,
      "closeness": 2,
      "firstInteraction": 1762310486384,
      "lastInteraction": 1762318365710,
      "rumors": []
    },
    "rottencheeseCA_rottencheeseCA": {
      "users": [
        "rottencheeseCA",
        "rottencheeseCA"
      ],
      "interactions": 4,
      "positiveInteractions": 0,
      "negativeInteractions": 0,
      "tension": 0,
      "closeness": 4,
      "firstInteraction": 1762310657909,
      "lastInteraction": 1762311400074,
      "rumors": []
    },
    "BoanerPains_BoanerPains": {
      "users": [
        "BoanerPains",
        "BoanerPains"
      ],
      "interactions": 2,
      "positiveInteractions": 0,
      "negativeInteractions": 0,
      "tension": 0,
      "closeness": 2,
      "firstInteraction": 1762312207787,
      "lastInteraction": 1762332164196,
      "rumors": []
    },
    "Brotherimbread_Brotherimbread": {
      "users": [
        "Brotherimbread",
        "Brotherimbread"
      ],
      "interactions": 16,
      "positiveInteractions": 0,
      "negativeInteractions": 0,
      "tension": 0,
      "closeness": 16,
      "firstInteraction": 1762312216291,
      "lastInteraction": 1762331381166,
      "rumors": []
    },
    "Ducky_Ducky": {
      "users": [
        "Ducky",
        "Ducky"
      ],
      "interactions": 3,
      "positiveInteractions": 0,
      "negativeInteractions": 0,
      "tension": 0,
      "closeness": 3,
      "firstInteraction": 1762312436411,
      "lastInteraction": 1762331276233,
      "rumors": []
    },
    "gangstalker_gangstalker": {
      "users": [
        "gangstalker",
        "gangstalker"
      ],
      "interactions": 5,
      "positiveInteractions": 0,
      "negativeInteractions": 0,
      "tension": 0,
      "closeness": 5,
      "firstInteraction": 1762312496165,
      "lastInteraction": 1762321840013,
      "rumors": []
    },
    "doscomputer_doscomputer": {
      "users": [
        "doscomputer",
        "doscomputer"
      ],
      "interactions": 2,
      "positiveInteractions": 0,
      "negativeInteractions": 0,
      "tension": 0,
      "closeness": 2,
      "firstInteraction": 1762312739769,
      "lastInteraction": 1762312935242,
      "rumors": []
    },
    "Wing Gweeps_Wing Gweeps": {
      "users": [
        "Wing Gweeps",
        "Wing Gweeps"
      ],
      "interactions": 2,
      "positiveInteractions": 0,
      "negativeInteractions": 0,
      "tension": 0,
      "closeness": 2,
      "firstInteraction": 1762312848938,
      "lastInteraction": 1762313468187,
      "rumors": []
    },
    "FifthCouncil_FifthCouncil": {
      "users": [
        "FifthCouncil",
        "FifthCouncil"
      ],
      "interactions": 1,
      "positiveInteractions": 0,
      "negativeInteractions": 0,
      "tension": 0,
      "closeness": 1,
      "firstInteraction": 1762313087306,
      "lastInteraction": 1762313087306,
      "rumors": []
    },
    "proud white cumstain man_proud white cumstain man": {
      "users": [
        "proud white cumstain man",
        "proud white cumstain man"
      ],
      "interactions": 1,
      "positiveInteractions": 0,
      "negativeInteractions": 0,
      "tension": 0,
      "closeness": 1,
      "firstInteraction": 1762313574808,
      "lastInteraction": 1762313574808,
      "rumors": []
    },
    "chumchum_yum_chumchum_yum": {
      "users": [
        "chumchum_yum",
        "chumchum_yum"
      ],
      "interactions": 1,
      "positiveInteractions": 0,
      "negativeInteractions": 0,
      "tension": 0,
      "closeness": 1,
      "firstInteraction": 1762314561354,
      "lastInteraction": 1762314561354,
      "rumors": []
    },
    "kingofnowhere_kingofnowhere": {
      "users": [
        "kingofnowhere",
        "kingofnowhere"
      ],
      "interactions": 1,
      "positiveInteractions": 0,
      "negativeInteractions": 0,
      "tension": 0,
      "closeness": 1,
      "firstInteraction": 1762314841057,
      "lastInteraction": 1762314841057,
      "rumors": []
    },
    "Artimenner1_Artimenner1": {
      "users": [
        "Artimenner1",
        "Artimenner1"
      ],
      "interactions": 2,
      "positiveInteractions": 0,
      "negativeInteractions": 0,
      "tension": 0,
      "closeness": 2,
      "firstInteraction": 1762315647920,
      "lastInteraction": 1762315738292,
      "rumors": []
    },
    "ToLazy4Name_ToLazy4Name": {
      "users": [
        "ToLazy4Name",
        "ToLazy4Name"
      ],
      "interactions": 1,
      "positiveInteractions": 0,
      "negativeInteractions": 0,
      "tension": 0,
      "closeness": 1,
      "firstInteraction": 1762315944468,
      "lastInteraction": 1762315944468,
      "rumors": []
    },
    "wowman_wowman": {
      "users": [
        "wowman",
        "wowman"
      ],
      "interactions": 4,
      "positiveInteractions": 0,
      "negativeInteractions": 0,
      "tension": 0,
      "closeness": 4,
      "firstInteraction": 1762316273628,
      "lastInteraction": 1762318707650,
      "rumors": []
    },
    "Scourge_Scourge": {
      "users": [
        "Scourge",
        "Scourge"
      ],
      "interactions": 2,
      "positiveInteractions": 0,
      "negativeInteractions": 0,
      "tension": 0,
      "closeness": 2,
      "firstInteraction": 1762316809206,
      "lastInteraction": 1762320634888,
      "rumors": []
    },
    "HuculberryFinn_HuculberryFinn": {
      "users": [
        "HuculberryFinn",
        "HuculberryFinn"
      ],
      "interactions": 2,
      "positiveInteractions": 0,
      "negativeInteractions": 0,
      "tension": 0,
      "closeness": 2,
      "firstInteraction": 1762316914935,
      "lastInteraction": 1762322866532,
      "rumors": []
    },
    "glowInTheDark_glowInTheDark": {
      "users": [
        "glowInTheDark",
        "glowInTheDark"
      ],
      "interactions": 4,
      "positiveInteractions": 0,
      "negativeInteractions": 0,
      "tension": 0,
      "closeness": 4,
      "firstInteraction": 1762317646957,
      "lastInteraction": 1762318840671,
      "rumors": []
    },
    "UncleDoctor_UncleDoctor": {
      "users": [
        "UncleDoctor",
        "UncleDoctor"
      ],
      "interactions": 4,
      "positiveInteractions": 0,
      "negativeInteractions": 0,
      "tension": 0,
      "closeness": 4,
      "firstInteraction": 1762319765217,
      "lastInteraction": 1762383355682,
      "rumors": []
    },
    "ducky125_ducky125": {
      "users": [
        "ducky125",
        "ducky125"
      ],
      "interactions": 1,
      "positiveInteractions": 0,
      "negativeInteractions": 0,
      "tension": 0,
      "closeness": 1,
      "firstInteraction": 1762324428694,
      "lastInteraction": 1762324428694,
      "rumors": []
    },
    "OMNI_OMNI": {
      "users": [
        "OMNI",
        "OMNI"
      ],
      "interactions": 1,
      "positiveInteractions": 0,
      "negativeInteractions": 0,
      "tension": 0,
      "closeness": 1,
      "firstInteraction": 1762324673059,
      "lastInteraction": 1762324673059,
      "rumors": []
    },
    "yallahabibis_yallahabibis": {
      "users": [
        "yallahabibis",
        "yallahabibis"
      ],
      "interactions": 2,
      "positiveInteractions": 0,
      "negativeInteractions": 0,
      "tension": 0,
      "closeness": 2,
      "firstInteraction": 1762326050125,
      "lastInteraction": 1762326053567,
      "rumors": []
    },
    "Phagsgiving_Phagsgiving": {
      "users": [
        "Phagsgiving",
        "Phagsgiving"
      ],
      "interactions": 1,
      "positiveInteractions": 0,
      "negativeInteractions": 0,
      "tension": 0,
      "closeness": 1,
      "firstInteraction": 1762326217202,
      "lastInteraction": 1762326217202,
      "rumors": []
    },
    "electriqwizard_electriqwizard": {
      "users": [
        "electriqwizard",
        "electriqwizard"
      ],
      "interactions": 1,
      "positiveInteractions": 0,
      "negativeInteractions": 0,
      "tension": 0,
      "closeness": 1,
      "firstInteraction": 1762326282027,
      "lastInteraction": 1762326282027,
      "rumors": []
    },
    "OrbMeat_OrbMeat": {
      "users": [
        "OrbMeat",
        "OrbMeat"
      ],
      "interactions": 4,
      "positiveInteractions": 0,
      "negativeInteractions": 0,
      "tension": 0,
      "closeness": 4,
      "firstInteraction": 1762329758142,
      "lastInteraction": 1762381971487,
      "rumors": []
    },
    "Val_Val": {
      "users": [
        "Val",
        "Val"
      ],
      "interactions": 1,
      "positiveInteractions": 0,
      "negativeInteractions": 0,
      "tension": 0,
      "closeness": 1,
      "firstInteraction": 1762332057488,
      "lastInteraction": 1762332057488,
      "rumors": []
    },
    "bangbangbangbang_bangbangbangbang": {
      "users": [
        "bangbangbangbang",
        "bangbangbangbang"
      ],
      "interactions": 1,
      "positiveInteractions": 0,
      "negativeInteractions": 0,
      "tension": 0,
      "closeness": 1,
      "firstInteraction": 1762384074246,
      "lastInteraction": 1762384074246,
      "rumors": []
    },
    "milk_man_milk_man": {
      "users": [
        "milk_man",
        "milk_man"
      ],
      "interactions": 2,
      "positiveInteractions": 0,
      "negativeInteractions": 0,
      "tension": 0,
      "closeness": 2,
      "firstInteraction": 1762384289584,
      "lastInteraction": 1762384298178,
      "rumors": []
    },
    "Applecooler_Applecooler": {
      "users": [
        "Applecooler",
        "Applecooler"
      ],
      "interactions": 1,
      "positiveInteractions": 0,
      "negativeInteractions": 0,
      "tension": 0,
      "closeness": 1,
      "firstInteraction": 1762384379729,
      "lastInteraction": 1762384379729,
      "rumors": []
    },
    "Klumb_Klumb": {
      "users": [
        "Klumb",
        "Klumb"
      ],
      "interactions": 1,
      "positiveInteractions": 0,
      "negativeInteractions": 0,
      "tension": 0,
      "closeness": 1,
      "firstInteraction": 1762384464869,
      "lastInteraction": 1762384464869,
      "rumors": []
    },
    "Taikunoaku_Taikunoaku": {
      "users": [
        "Taikunoaku",
        "Taikunoaku"
      ],
      "interactions": 2,
      "positiveInteractions": 0,
      "negativeInteractions": 0,
      "tension": 0,
      "closeness": 2,
      "firstInteraction": 1762384675140,
      "lastInteraction": 1762385006236,
      "rumors": []
    },
    "Carpentria Booty Nourishment_Carpentria Booty Nourishment": {
      "users": [
        "Carpentria Booty Nourishment",
        "Carpentria Booty Nourishment"
      ],
      "interactions": 1,
      "positiveInteractions": 0,
      "negativeInteractions": 0,
      "tension": 0,
      "closeness": 1,
      "firstInteraction": 1762384880181,
      "lastInteraction": 1762384880181,
      "rumors": []
    }
  },
  "rumors": {},
  "trustNetwork": {
    "You": [
      "You"
    ]
  },
  "rumorIdCounter": 0,
  "gossipPropensity": 0.5
}